tai/.DS_Store
tai/core/.gitignore_template
tai/core/__init__.py
tai/core/cli.py
tai/core/gitea_api.ipynb
tai/core/gitea_conf.yaml
tai/core/gitea_controller.py
tai/core/install_tai.py
tai/core/utils.py
trusted_ai-0.1.18.dist-info/METADATA
trusted_ai-0.1.18.dist-info/WHEEL
trusted_ai-0.1.18.dist-info/entry_points.txt
trusted_ai-0.1.18.dist-info/RECORD
