Metadata-Version: 2.1
Name: trusted-ai
Version: 0.1.18
Summary: Trusted-ai project.
Author-Email: Ekaterina Kurdenkova <kurdenkova@ispras.ru>
License: MIT
Requires-Python: >=3.12
Requires-Dist: GitPython>=3.1.41
Requires-Dist: pdm>=2.11.2
Requires-Dist: pyyaml>=6.0.1
Requires-Dist: Sphinx>=7.2.6
Requires-Dist: furo>=2023.9.10
